mndino/__init__.py
mndino/detection.py
mndino/evaluation.py
mndino/mnds.py
mndino/mnmodel.py
mndino/utils/utils.py
mndino-0.0.0.3.dist-info/METADATA
mndino-0.0.0.3.dist-info/WHEEL
mndino-0.0.0.3.dist-info/licenses/LICENSE
mndino-0.0.0.3.dist-info/RECORD
