Metadata-Version: 2.4
Name: mndino
Version: 0.0.0.3
Summary: mn-DINO: [add description of the project later]
Project-URL: Homepage, https://github.com/CaicedoLab/micronuclei-detection/tree/main
Project-URL: Issues, https://github.com/CaicedoLab/micronuclei-detection/issues
Author: Niels Mailand
Author-email: Yifan Ren <yren86@wisc.edu>, Louise Morlot <louise.morlot@cpr.ku.dk>, Owen Andrews <oandrews@broadinstitute.org>, Emil Peter Thrane Hertz <emil.hertz@cpr.ku.dk>, Juan Caicedo <juan.caicedo@wisc.edu>
License-Expression: MIT
License-File: LICENSE
Classifier: Operating System :: OS Independent
Classifier: Programming Language :: Python :: 3
Requires-Python: >=3.10
Requires-Dist: matplotlib
Requires-Dist: numpy
Requires-Dist: pandas
Requires-Dist: pillow
Requires-Dist: scikit-image
Requires-Dist: scikit-learn
Requires-Dist: scipy
Requires-Dist: timm
Requires-Dist: torch
Requires-Dist: torchvision
Requires-Dist: tqdm
Requires-Dist: wandb
